{"namedChunkGroups":{"polyfill":{"name":"polyfill","assets":[{"name":"webpack-runtime-cda4d334663cce498d20.js","size":5081},{"name":"polyfill-b94e88c7412185faa2fa.js","size":93218}],"filteredAssets":0,"assetsSize":98299,"filteredAuxiliaryAssets":2,"auxiliaryAssetsSize":272111},"app":{"name":"app","assets":[{"name":"webpack-runtime-cda4d334663cce498d20.js","size":5081},{"name":"framework-20672aedb31a67a4f0ae.js","size":128961},{"name":"app-af25073b03aba748060b.js","size":74373}],"filteredAssets":0,"assetsSize":208415,"filteredAuxiliaryAssets":3,"auxiliaryAssetsSize":674379},"component---src-pages-404-js":{"name":"component---src-pages-404-js","assets":[{"name":"styles.ac46d673741bae581fd4.css","size":5384},{"name":"commons-8029785b798c4c419245.js","size":16790},{"name":"component---src-pages-404-js-1d2c1e275d588f4cc889.js","size":469}],"filteredAssets":0,"assetsSize":22643,"filteredAuxiliaryAssets":2,"auxiliaryAssetsSize":70313},"component---src-pages-using-typescript-tsx":{"name":"component---src-pages-using-typescript-tsx","assets":[{"name":"styles.ac46d673741bae581fd4.css","size":5384},{"name":"commons-8029785b798c4c419245.js","size":16790},{"name":"component---src-pages-using-typescript-tsx-3533779c4933c8a67b2b.js","size":1317}],"filteredAssets":0,"assetsSize":23491,"filteredAuxiliaryAssets":2,"auxiliaryAssetsSize":71733},"component---src-templates-page-js":{"name":"component---src-templates-page-js","assets":[{"name":"styles.ac46d673741bae581fd4.css","size":5384},{"name":"commons-8029785b798c4c419245.js","size":16790},{"name":"component---src-templates-page-js-013a902d3e1385bb4f13.js","size":2311}],"filteredAssets":0,"assetsSize":24485,"filteredAuxiliaryAssets":2,"auxiliaryAssetsSize":72331},"one":{"name":"one","assets":[{"name":"one-b65be21f430363bb6dde.js","size":299}],"filteredAssets":0,"assetsSize":299,"filteredAuxiliaryAssets":1,"auxiliaryAssetsSize":474},"two":{"name":"two","assets":[{"name":"two-5b4381fbb2b98235b306.js","size":296}],"filteredAssets":0,"assetsSize":296,"filteredAuxiliaryAssets":1,"auxiliaryAssetsSize":473},"three":{"name":"three","assets":[{"name":"three-dec6b3ad19f62b6f0a6b.js","size":300}],"filteredAssets":0,"assetsSize":300,"filteredAuxiliaryAssets":1,"auxiliaryAssetsSize":481}},"assetsByChunkName":{"polyfill":["webpack-runtime-cda4d334663cce498d20.js","polyfill-b94e88c7412185faa2fa.js"],"app":["webpack-runtime-cda4d334663cce498d20.js","framework-20672aedb31a67a4f0ae.js","app-af25073b03aba748060b.js"],"component---src-pages-404-js":["styles.ac46d673741bae581fd4.css","commons-8029785b798c4c419245.js","component---src-pages-404-js-1d2c1e275d588f4cc889.js"],"component---src-pages-using-typescript-tsx":["styles.ac46d673741bae581fd4.css","commons-8029785b798c4c419245.js","component---src-pages-using-typescript-tsx-3533779c4933c8a67b2b.js"],"component---src-templates-page-js":["styles.ac46d673741bae581fd4.css","commons-8029785b798c4c419245.js","component---src-templates-page-js-013a902d3e1385bb4f13.js"],"one":["one-b65be21f430363bb6dde.js"],"two":["two-5b4381fbb2b98235b306.js"],"three":["three-dec6b3ad19f62b6f0a6b.js"]},"childAssetsByChunkName":{}}